modality/__init__.py
modality/attr.py
modality/client.py
modality-0.1.0.dist-info/METADATA
modality-0.1.0.dist-info/WHEEL
modality-0.1.0.dist-info/licenses/LICENSE
modality-0.1.0.dist-info/RECORD
