Metadata-Version: 2.1
Name: modality
Version: 0.1.0
Summary: A python client library for the Modality API
Project-URL: Homepage, https://github.com/auxoncorp/modality-sdk/client-libraries/python
Project-URL: Bug Tracker, https://github.com/auxoncorp/modality-sdk/issues
Author-email: Russell Mull <russell@auxon.io>
License-File: LICENSE
Classifier: License :: OSI Approved :: Apache Software License
Classifier: Operating System :: OS Independent
Classifier: Programming Language :: Python :: 3
Requires-Python: >=3.7
